odoo/addons/contract_variable_qty_prorated/README.rst
odoo/addons/contract_variable_qty_prorated/__init__.py
odoo/addons/contract_variable_qty_prorated/__manifest__.py
odoo/addons/contract_variable_qty_prorated/data/contract_variable_qty_prorated.xml
odoo/addons/contract_variable_qty_prorated/i18n/contract_variable_qty_prorated.pot
odoo/addons/contract_variable_qty_prorated/i18n/fr.po
odoo/addons/contract_variable_qty_prorated/i18n/it.po
odoo/addons/contract_variable_qty_prorated/i18n/nl.po
odoo/addons/contract_variable_qty_prorated/i18n/nl_NL.po
odoo/addons/contract_variable_qty_prorated/i18n/pt_BR.po
odoo/addons/contract_variable_qty_prorated/i18n/sv.po
odoo/addons/contract_variable_qty_prorated/models/__init__.py
odoo/addons/contract_variable_qty_prorated/models/contract_line.py
odoo/addons/contract_variable_qty_prorated/readme/CONTRIBUTORS.md
odoo/addons/contract_variable_qty_prorated/readme/DESCRIPTION.md
odoo/addons/contract_variable_qty_prorated/readme/ROADMAP.md
odoo/addons/contract_variable_qty_prorated/static/description/icon.png
odoo/addons/contract_variable_qty_prorated/static/description/index.html
odoo/addons/contract_variable_qty_prorated/tests/__init__.py
odoo/addons/contract_variable_qty_prorated/tests/test_compute_proprata.py
odoo/addons/contract_variable_qty_prorated/views/contract_template_line.xml
odoo_addon_contract_variable_qty_prorated-18.0.1.0.0.8.dist-info/METADATA
odoo_addon_contract_variable_qty_prorated-18.0.1.0.0.8.dist-info/WHEEL
odoo_addon_contract_variable_qty_prorated-18.0.1.0.0.8.dist-info/top_level.txt
odoo_addon_contract_variable_qty_prorated-18.0.1.0.0.8.dist-info/RECORD
